eicmcio/__init__.py
eicmcio/detect.py
eicmcio/file_types.py
eicmcio/generic_reader.py
eicmcio/version.py
eicmcio-0.0.2.dist-info/LICENSE
eicmcio-0.0.2.dist-info/METADATA
eicmcio-0.0.2.dist-info/WHEEL
eicmcio-0.0.2.dist-info/entry_points.txt
eicmcio-0.0.2.dist-info/top_level.txt
eicmcio-0.0.2.dist-info/RECORD
