Metadata-Version: 2.1
Name: eicmcio
Version: 0.0.2
Summary: EIC Monte-Carlo io library
Home-page: https://github.com/eic/eicmcio
Author: Dmitry Romanov
Author-email: romanov@jlab.org
License: MIT
Platform: UNKNOWN
Classifier: Development Status :: 4 - Beta
Classifier: License :: OSI Approved :: MIT License
Classifier: Programming Language :: Python :: 2
Classifier: Programming Language :: Python :: 2.7
Classifier: Programming Language :: Python :: 3
Classifier: Programming Language :: Python :: 3.6
Requires-Dist: HepMC3
